PermutiveAPI/Cohort.py
PermutiveAPI/Segmentation.py
PermutiveAPI/Workspace.py
PermutiveAPI/__init__.py
PermutiveAPI/py.typed
PermutiveAPI/Audience/Import.py
PermutiveAPI/Audience/Segment.py
PermutiveAPI/Audience/Source.py
PermutiveAPI/Audience/__init__.py
PermutiveAPI/Identify/Alias.py
PermutiveAPI/Identify/Identity.py
PermutiveAPI/Identify/__init__.py
PermutiveAPI/_Utils/__init__.py
PermutiveAPI/_Utils/file.py
PermutiveAPI/_Utils/http.py
PermutiveAPI/_Utils/json.py
PermutiveAPI/_Utils/list.py
permutiveapi-5.4.4.dist-info/licenses/LICENSE
permutiveapi-5.4.4.dist-info/METADATA
permutiveapi-5.4.4.dist-info/WHEEL
permutiveapi-5.4.4.dist-info/top_level.txt
permutiveapi-5.4.4.dist-info/RECORD
