Metadata-Version: 2.4
Name: PermutiveAPI
Version: 5.4.4
Summary: A Python wrapper for the Permutive API.
Author-email: fatmambo33 <fatmambo33@gmail.com>
License: MIT License
Classifier: Development Status :: 5 - Production/Stable
Classifier: Intended Audience :: Developers
Classifier: Operating System :: OS Independent
Classifier: Programming Language :: Python :: 3
Classifier: Programming Language :: Python :: 3.8
Classifier: Programming Language :: Python :: 3.9
Classifier: Programming Language :: Python :: 3.10
Classifier: Programming Language :: Python :: 3.11
Classifier: Programming Language :: Python :: 3.12
Classifier: Topic :: Software Development :: Libraries :: Python Modules
Requires-Python: >=3.8
License-File: LICENSE
Requires-Dist: requests
Requires-Dist: python-dotenv
Requires-Dist: pandas
Provides-Extra: dev
Requires-Dist: pydocstyle; extra == "dev"
Requires-Dist: pytest-pydocstyle; extra == "dev"
Requires-Dist: pyright; extra == "dev"
Requires-Dist: black; extra == "dev"
Requires-Dist: pytest-cov; extra == "dev"
Dynamic: license-file
